semaphore-0.4.65.dist-info/top_level.txt
semaphore-0.4.65.dist-info/RECORD
semaphore-0.4.65.dist-info/METADATA
semaphore-0.4.65.dist-info/WHEEL
semaphore/_compat.py
semaphore/envelope.py
semaphore/_lowlevel__lib.so
semaphore/exceptions.py
semaphore/utils.py
semaphore/processing.py
semaphore/auth.py
semaphore/consts.py
semaphore/__init__.py
semaphore/_lowlevel__ffi.py
semaphore/_lowlevel.py
