Metadata-Version: 2.1
Name: semaphore
Version: 0.4.65
Summary: A python library to access sentry relay functionality.
Home-page: UNKNOWN
Author: Sentry
Author-email: hello@sentry.io
License: BSL-1.1
Platform: any
Requires-Dist: milksnake (>=0.1.2)
